convai_innovations/__init__.py
convai_innovations/ai_systems.py
convai_innovations/ai_tutor_narrator.py
convai_innovations/cli.py
convai_innovations/code_narrator.py
convai_innovations/convai.py
convai_innovations/conversation_storage.py
convai_innovations/models.py
convai_innovations/realtime_tutor.py
convai_innovations/sandbox_manager.py
convai_innovations/session_manager.py
convai_innovations/ui_components.py
convai_innovations/utils.py
convai_innovations/visualizations.py
convai_innovations-1.2.0.dist-info/licenses/LICENSE
convai_innovations-1.2.0.dist-info/METADATA
convai_innovations-1.2.0.dist-info/WHEEL
convai_innovations-1.2.0.dist-info/entry_points.txt
convai_innovations-1.2.0.dist-info/top_level.txt
convai_innovations-1.2.0.dist-info/RECORD
