Metadata-Version: 2.4
Name: convai-innovations
Version: 1.2.0
Summary: Interactive LLM Training Academy - Learn to build language models from scratch
Home-page: https://github.com/ConvAI-Innovations/ailearning
Author: ConvAI Innovations
Author-email: ConvAI Innovations <support@convai-innovations.com>
Maintainer-email: ConvAI Innovations <support@convai-innovations.com>
License: ### GNU GENERAL PUBLIC LICENSE
Project-URL: Homepage, https://github.com/ConvAI-Innovations/ailearning
Project-URL: Documentation, https://convai-innovations.readthedocs.io/
Project-URL: Repository, https://github.com/ConvAI-Innovations/ailearning.git
Project-URL: Bug Tracker, https://github.com/ConvAI-Innovations/ailearning/issues
Project-URL: Changelog, https://github.com/ConvAI-Innovations/ailearning/blob/main/CHANGELOG.md
Keywords: machine-learning,deep-learning,llm,education,pytorch,transformer,ai-training,interactive-learning,neural-networks
Classifier: Development Status :: 4 - Beta
Classifier: Intended Audience :: Education
Classifier: Intended Audience :: Developers
Classifier: Intended Audience :: Science/Research
Classifier: License :: OSI Approved :: GNU General Public License v3 (GPLv3)
Classifier: Operating System :: OS Independent
Classifier: Programming Language :: Python :: 3
Classifier: Programming Language :: Python :: 3.11
Classifier: Programming Language :: Python :: 3.12
Classifier: Programming Language :: Python :: 3.13
Classifier: Topic :: Education
Classifier: Topic :: Scientific/Engineering :: Artificial Intelligence
Classifier: Topic :: Software Development :: Libraries :: Python Modules
Requires-Python: >=3.8
License-File: LICENSE
Requires-Dist: numpy==2.3.4
Requires-Dist: scipy==1.16.2
Requires-Dist: scikit-learn==1.7.2
Requires-Dist: torch==2.6.0
Requires-Dist: transformers==4.51.3
Requires-Dist: requests==2.32.3
Requires-Dist: argostranslate==1.9.6
Requires-Dist: kokoro==0.9.4
Requires-Dist: sounddevice==0.5.2
Provides-Extra: audio
Requires-Dist: kokoro==0.9.4; extra == "audio"
Requires-Dist: sounddevice==0.5.2; extra == "audio"
Provides-Extra: dev
Requires-Dist: pytest>=7.0.0; extra == "dev"
Requires-Dist: pytest-cov>=4.0.0; extra == "dev"
Requires-Dist: black>=22.0.0; extra == "dev"
Requires-Dist: flake8>=5.0.0; extra == "dev"
Requires-Dist: mypy>=1.0.0; extra == "dev"
Requires-Dist: build>=0.10.0; extra == "dev"
Requires-Dist: twine>=4.0.0; extra == "dev"
Provides-Extra: all
Requires-Dist: convai-innovations[audio,dev]; extra == "all"
Dynamic: author
Dynamic: home-page
Dynamic: license-file
Dynamic: requires-python
